spam_detector/__init__.py
spam_detector/cli.py
spam_detector_cli-1.1.0.dist-info/METADATA
spam_detector_cli-1.1.0.dist-info/WHEEL
spam_detector_cli-1.1.0.dist-info/entry_points.txt
spam_detector_cli-1.1.0.dist-info/top_level.txt
spam_detector_cli-1.1.0.dist-info/RECORD
