Metadata-Version: 2.4
Name: spam-detector-cli
Version: 1.1.0
Summary: A simple CLI tool to detect spam messages
Author: Boenzoel
Author-email: Nama Kamu <email@example.com>
Requires-Python: >=3.7
Requires-Dist: scikit-learn
Requires-Dist: pandas
Dynamic: author
Dynamic: requires-python
